LICENSE.txt
MANIFEST.in
README.rst
setup.py
jira/__init__.py
jira/rpc.py
jira/rpc_utils.py
jira_rpc.egg-info/PKG-INFO
jira_rpc.egg-info/SOURCES.txt
jira_rpc.egg-info/dependency_links.txt
jira_rpc.egg-info/top_level.txt