Metadata-Version: 1.1
Name: jira-rpc
Version: 0.1
Summary: Python client for JIRA SOAP API
Home-page: https://github.com/Maplecroft/jira-rpc
Author: James Rutherford
Author-email: james.rutherford@maplecroft.com
License: UNKNOWN
Keywords: jira,rpc
Platform: UNKNOWN
Classifier: Development Status :: 4 - Beta
Classifier: Environment :: Other Environment
Classifier: Intended Audience :: Developers
Classifier: License :: OSI Approved :: MIT License
Classifier: Operating System :: OS Independent
Classifier: Programming Language :: Python
Classifier: Programming Language :: Python :: 2.6
Classifier: Programming Language :: Python :: 2.7
Classifier: Topic :: Internet :: WWW/HTTP
Provides: jira
